econometrics_olsandmore/__init__.py
econometrics_olsandmore/correlation.py
econometrics_olsandmore/diagnostics.py
econometrics_olsandmore/multicollinearity.py
econometrics_olsandmore/regression.py
econometrics_olsandmore/unit_root.py
econometrics_olsandmore/tests/__init__.py
econometrics_olsandmore/tests/test_adf.py
econometrics_olsandmore/tests/test_breusch_godfrey.py
econometrics_olsandmore/tests/test_correlation.py
econometrics_olsandmore/tests/test_diagnostics.py
econometrics_olsandmore/tests/test_hetroskedasticity.py
econometrics_olsandmore/tests/test_jarque_bera.py
econometrics_olsandmore/tests/test_predict.py
econometrics_olsandmore/tests/test_regression.py
econometrics_olsandmore/tests/test_validation.py
econometrics_olsandmore/tests/test_vif.py
econometrics_olsandmore/tests/test_white.py
econometrics_olsandmore-0.1.0.dist-info/METADATA
econometrics_olsandmore-0.1.0.dist-info/WHEEL
econometrics_olsandmore-0.1.0.dist-info/top_level.txt
econometrics_olsandmore-0.1.0.dist-info/RECORD
