Metadata-Version: 2.4
Name: econometrics_olsandmore
Version: 0.1.0
Summary: Econometrics library: manual OLS + diagnostics (DW, BP, White, JB, BG), VIF, correlation, ADF
Author: Octavio Pacheco
License: MIT
Requires-Python: >=3.10
Requires-Dist: numpy
Requires-Dist: pandas
Requires-Dist: scipy
